hikingmap/__init__.py
hikingmap/__main__.py
hikingmap/area.py
hikingmap/coordinate.py
hikingmap/hikingmap.py
hikingmap/page.py
hikingmap/trackfinder.py
hikingmap/tracks.py
hikingmap-0.1.0.dist-info/LICENSE
hikingmap-0.1.0.dist-info/METADATA
hikingmap-0.1.0.dist-info/WHEEL
hikingmap-0.1.0.dist-info/entry_points.txt
hikingmap-0.1.0.dist-info/top_level.txt
hikingmap-0.1.0.dist-info/RECORD
