Metadata-Version: 2.1
Name: hikingmap
Version: 0.1.0
Summary: A script to calculate the minimum amount of pages needed to render one or more GPX tracks
Home-page: https://github.com/roelderickx/hikingmap
Author: Roel Derickx
Author-email: hikingmap.pypi@derickx.be
License: GNU General Public License (GNU GPL v3 or above)
Platform: UNKNOWN
Classifier: Environment :: Console
Classifier: Topic :: Scientific/Engineering :: GIS
Classifier: Development Status :: 6 - Mature
Classifier: Programming Language :: Python :: 3
Classifier: License :: OSI Approved :: GNU General Public License (GPL)
Classifier: Operating System :: OS Independent
Requires-Python: >=3.7
